qra/__init__.py
qra/cli.py
qra/core.py
qra/server.py
qra/templates/__init__.py
qra/templates/basic/index.html
qra/templates/basic/script.js
qra/templates/basic/styles.css
qra/templates/blog/index.html
qra/templates/blog/script.js
qra/templates/blog/styles.css
qra/templates/docs/index.html
qra/templates/docs/script.js
qra/templates/docs/styles.css
qra/templates/makrdown/index.html
qra/templates/makrdown/script.js
qra/templates/makrdown/styles.css
qra/templates/manager.py
qra/templates/portfolio/index.html
qra/templates/portfolio/script.js
qra/templates/portfolio/styles.css
qra-0.1.5.dist-info/LICENSE
qra-0.1.5.dist-info/METADATA
qra-0.1.5.dist-info/WHEEL
qra-0.1.5.dist-info/entry_points.txt
qra-0.1.5.dist-info/RECORD
