Metadata-Version: 2.3
Name: qra
Version: 0.1.5
Summary: MHTML editor and processor with live preview
Author: Tom Sapletta
Author-email: info@softreck.dev
Requires-Python: >=3.8.1,<4.0
Classifier: Programming Language :: Python :: 3
Classifier: Programming Language :: Python :: 3.9
Classifier: Programming Language :: Python :: 3.10
Classifier: Programming Language :: Python :: 3.11
Classifier: Programming Language :: Python :: 3.12
Classifier: Programming Language :: Python :: 3.13
Requires-Dist: beautifulsoup4 (>=4.12.0,<5.0.0)
Requires-Dist: click (>=8.1.0,<9.0.0)
Requires-Dist: email-validator (>=2.0.0,<3.0.0)
Requires-Dist: flask (>=2.3.0,<3.0.0)
Requires-Dist: jinja2 (>=3.1.0,<4.0.0)
Requires-Dist: markdown (>=3.5.0,<4.0.0)
Requires-Dist: pygments (>=2.16.0,<3.0.0)
Requires-Dist: watchdog (>=3.0.0,<4.0.0)
